{
  "metrics": {
    "avg_5star_pulls": [
      [0, 12.45],
      [5, 15],
      [10, 15.31],
      [15, 15.5],
      [20, 15.69],
      [25, 15.83],
      [30, 15.95],
      [35, 16.07],
      [40, 16.17],
      [45, 16.28],
      [50, 16.38],
      [55, 16.49],
      [60, 16.58],
      [65, 16.69],
      [70, 16.78],
      [75, 16.91],
      [80, 17.04],
      [85, 17.17],
      [90, 17.36],
      [95, 17.62],
      [100, 19.31]
    ],
    "total_pulls_per_user": [
      [0, 1],
      [5, 258.3],
      [10, 410],
      [15, 519],
      [20, 587],
      [25, 657.75],
      [30, 715.9],
      [35, 778.05],
      [40, 822],
      [45, 870],
      [50, 925],
      [55, 971],
      [60, 1020],
      [65, 1076.95],
      [70, 1134.1],
      [75, 1203.25],
      [80, 1284.8],
      [85, 1416],
      [90, 1611.5],
      [95, 1942.85],
      [100, 5690]
    ],
    "avg_4star_pulls_type2": [
      [0, 6.71],
      [5, 8.03],
      [10, 8.16],
      [15, 8.28],
      [20, 8.34],
      [25, 8.41],
      [30, 8.47],
      [35, 8.52],
      [40, 8.56],
      [45, 8.59],
      [50, 8.64],
      [55, 8.68],
      [60, 8.72],
      [65, 8.75],
      [70, 8.8],
      [75, 8.84],
      [80, 8.89],
      [85, 8.98],
      [90, 9.07],
      [95, 9.2],
      [100, 10]
    ],
    "avg_4star_pulls_type3": [
      [0, 2.71],
      [5, 3.62],
      [10, 3.71],
      [15, 3.77],
      [20, 3.82],
      [25, 3.86],
      [30, 3.9],
      [35, 3.93],
      [40, 3.96],
      [45, 3.98],
      [50, 4.01],
      [55, 4.04],
      [60, 4.06],
      [65, 4.09],
      [70, 4.12],
      [75, 4.15],
      [80, 4.19],
      [85, 4.22],
      [90, 4.28],
      [95, 4.36],
      [100, 5]
    ]
  },
  "generated_at": "2025-06-30T03:30:00Z"
}
